fileformats/extras/application/__init__.py
fileformats/extras/application/archive.py
fileformats/extras/application/medical.py
fileformats/extras/application/serialization.py
fileformats/extras/application/tests/test_application_archive.py
fileformats/extras/application/tests/test_application_medical.py
fileformats/extras/application/tests/test_application_serialization.py
fileformats/extras/audio/__init__.py
fileformats/extras/core/__init__.py
fileformats/extras/core/_version.py
fileformats/extras/core/tests/test_converter.py
fileformats/extras/core/tests/test_import_check.py
fileformats/extras/generic/__init__.py
fileformats/extras/generic/converters.py
fileformats/extras/generic/tests/test_converters.py
fileformats/extras/image/__init__.py
fileformats/extras/image/converters.py
fileformats/extras/image/readwrite.py
fileformats/extras/image/tests/test_image_converters.py
fileformats/extras/model/__init__.py
fileformats/extras/testing/__init__.py
fileformats/extras/text/__init__.py
fileformats/extras/text/load_save.py
fileformats/extras/vendor/openxmlformats_officedocument/application.py
fileformats/extras/video/__init__.py
fileformats_extras-0.17.3.dist-info/METADATA
fileformats_extras-0.17.3.dist-info/WHEEL
fileformats_extras-0.17.3.dist-info/licenses/LICENSE
fileformats_extras-0.17.3.dist-info/RECORD
