Metadata-Version: 2.4
Name: fileformats-extras
Version: 0.17.3
Summary: Extra methods for accessing and manipulating the underlying data referenced by fileformats classes
Project-URL: repository, https://github.com/ArcanaFramework/fileformats
Author-email: "Thomas G. Close" <tom.g.close@gmail.com>
Maintainer-email: "Thomas G. Close" <tom.g.close@gmail.com>
License: Creative Commons Attribution 4.0 International Public License
License-File: LICENSE
Keywords: data,file formats
Classifier: Development Status :: 3 - Alpha
Classifier: Environment :: Console
Classifier: Intended Audience :: Science/Research
Classifier: License :: OSI Approved :: Apache Software License
Classifier: Operating System :: MacOS :: MacOS X
Classifier: Operating System :: Microsoft :: Windows
Classifier: Operating System :: POSIX :: Linux
Classifier: Programming Language :: Python :: 3.11
Classifier: Programming Language :: Python :: 3.12
Classifier: Programming Language :: Python :: 3.13
Classifier: Topic :: Scientific/Engineering
Requires-Python: >=3.11
Requires-Dist: fileformats
Requires-Dist: pydra>=1.0a
Provides-Extra: application
Requires-Dist: medimages4tests; extra == 'application'
Requires-Dist: pydicom>=2.3; extra == 'application'
Requires-Dist: pyyaml>=6.0; extra == 'application'
Provides-Extra: audio
Provides-Extra: dev
Requires-Dist: black; extra == 'dev'
Requires-Dist: codespell; extra == 'dev'
Requires-Dist: flake8; extra == 'dev'
Requires-Dist: flake8-pyproject; extra == 'dev'
Requires-Dist: pre-commit; extra == 'dev'
Provides-Extra: image
Requires-Dist: imageio>=2.24.0; extra == 'image'
Provides-Extra: model
Provides-Extra: test
Requires-Dist: codecov; extra == 'test'
Requires-Dist: pytest-cov>=2.12.1; extra == 'test'
Requires-Dist: pytest-env>=0.6.2; extra == 'test'
Requires-Dist: pytest>=6.2.5; extra == 'test'
Provides-Extra: text
Provides-Extra: vendor-openxmlformats-officedocument
Requires-Dist: python-docx>=1.2.0; extra == 'vendor-openxmlformats-officedocument'
Provides-Extra: video
